{
  "last_checked_at": "2026-07-21T04:30:54.237980+00:00",
  "products": {
    "1111020c1": {
      "last_seen_at": "2026-07-21T04:30:54.237268+00:00",
      "name": "Principal matcha Tenju \u00a520,100+ $123.73+ \u20ac 108 .39+ \u00a3 92 .04+ \u00a5835 .96+",
      "status": "OUT_OF_STOCK",
      "url": "https://www.marukyu-koyamaen.co.jp/english/shop/products/1111020c1"
    },
    "1112020c1": {
      "last_seen_at": "2026-07-21T04:30:54.237417+00:00",
      "name": "Urasenke Konnichian HOUNSAI Sosho Urasenke School Favored Matcha Keichi no Mukashi \u00a54,700+ $28.93+ \u20ac 25 .35+ \u00a3 21 .52+ \u00a5195 .47+",
      "status": "OUT_OF_STOCK",
      "url": "https://www.marukyu-koyamaen.co.jp/english/shop/products/1112020c1"
    },
    "1114020c1": {
      "last_seen_at": "2026-07-21T04:30:54.237624+00:00",
      "name": "Mushakoji Senke Kankyuan FUTETSUSAI Iemoto Mushakojisenke School Favored Matcha Suisho no Mukashi \u00a53,700+ $22.78+ \u20ac 19 .95+ \u00a3 16 .94+ \u00a5153 .88+",
      "status": "OUT_OF_STOCK",
      "url": "https://www.marukyu-koyamaen.co.jp/english/shop/products/1114020c1"
    },
    "1115020c1": {
      "last_seen_at": "2026-06-26T01:55:54.405546+00:00",
      "name": "Limited Edition Teas Shin Matcha Hatsu Enishi $26.58+",
      "status": "OUT_OF_STOCK",
      "url": "https://www.marukyu-koyamaen.co.jp/english/shop/products/1115020c1"
    },
    "1121020c1": {
      "last_seen_at": "2026-07-21T04:30:54.236929+00:00",
      "name": "Principal matcha Choan \u00a57,150+ $44.01+ \u20ac 38 .56+ \u00a3 32 .74+ \u00a5297 .37+",
      "status": "IN_STOCK",
      "url": "https://www.marukyu-koyamaen.co.jp/english/shop/products/1121020c1"
    },
    "1122020c1": {
      "last_seen_at": "2026-07-21T04:30:54.237436+00:00",
      "name": "Urasenke Konnichian HOUNSAI Sosho Urasenke School Favored Matcha Kiun \u00a53,700+ $22.78+ \u20ac 19 .95+ \u00a3 16 .94+ \u00a5153 .88+",
      "status": "OUT_OF_STOCK",
      "url": "https://www.marukyu-koyamaen.co.jp/english/shop/products/1122020c1"
    },
    "1124020c1": {
      "last_seen_at": "2026-07-21T04:30:54.237641+00:00",
      "name": "Mushakoji Senke Kankyuan FUTETSUSAI Iemoto Mushakojisenke School Favored Matcha Shofu \u00a52,400+ $14.77+ \u20ac 12 .94+ \u00a3 10 .99+ \u00a599 .82+",
      "status": "OUT_OF_STOCK",
      "url": "https://www.marukyu-koyamaen.co.jp/english/shop/products/1124020c1"
    },
    "1131020c1": {
      "last_seen_at": "2026-07-21T04:30:54.236995+00:00",
      "name": "Principal matcha Eiju \u00a54,700+ $28.93+ \u20ac 25 .35+ \u00a3 21 .52+ \u00a5195 .47+",
      "status": "IN_STOCK",
      "url": "https://www.marukyu-koyamaen.co.jp/english/shop/products/1131020c1"
    },
    "1132020c1": {
      "last_seen_at": "2026-07-21T04:30:54.237455+00:00",
      "name": "Urasenke Konnichian HOUNSAI Sosho Urasenke School Favored Matcha Tama no Shiro \u00a52,400+ $14.77+ \u20ac 12 .94+ \u00a3 10 .99+ \u00a599 .82+",
      "status": "OUT_OF_STOCK",
      "url": "https://www.marukyu-koyamaen.co.jp/english/shop/products/1132020c1"
    },
    "1134040c1": {
      "last_seen_at": "2026-07-21T04:30:54.237726+00:00",
      "name": "Daitokuji Temple Favored Daitokuji Temple Favored Matcha Itteikisui (GOLD) \u00a58,120 $49.98 \u20ac 43 .79 \u00a3 37 .18 \u00a5337 .71",
      "status": "OUT_OF_STOCK",
      "url": "https://www.marukyu-koyamaen.co.jp/english/shop/products/1134040c1"
    },
    "1141020c1": {
      "last_seen_at": "2026-07-21T04:30:54.237011+00:00",
      "name": "Principal matcha Unkaku \u00a53,700+ $22.78+ \u20ac 19 .95+ \u00a3 16 .94+ \u00a5153 .88+",
      "status": "IN_STOCK",
      "url": "https://www.marukyu-koyamaen.co.jp/english/shop/products/1141020c1"
    },
    "1142020c1": {
      "last_seen_at": "2026-07-21T04:30:54.237473+00:00",
      "name": "Urasenke Konnichian HOUNSAI Sosho Urasenke School Favored Matcha Shohaku \u00a52,000+ $12.31+ \u20ac 10 .79+ \u00a3 9 .16+ \u00a583 .18+",
      "status": "OUT_OF_STOCK",
      "url": "https://www.marukyu-koyamaen.co.jp/english/shop/products/1142020c1"
    },
    "1143020c1": {
      "last_seen_at": "2026-07-21T04:30:54.237709+00:00",
      "name": "Enshuryu Fudenan KOBORISOJITSU Iemoto Enshuryu School Favored Matcha Ichigen no Shiro \u00a53,700+ $22.78+ \u20ac 19 .95+ \u00a3 16 .94+ \u00a5153 .88+",
      "status": "OUT_OF_STOCK",
      "url": "https://www.marukyu-koyamaen.co.jp/english/shop/products/1143020c1"
    },
    "1144020c1": {
      "last_seen_at": "2026-07-21T04:30:54.237657+00:00",
      "name": "Yabunouchi Ennan SEISEISAI Iemoto Yabunouchi School Favored Matcha Seiwa no Shiro \u00a53,700+ $22.78+ \u20ac 19 .95+ \u00a3 16 .94+ \u00a5153 .88+",
      "status": "OUT_OF_STOCK",
      "url": "https://www.marukyu-koyamaen.co.jp/english/shop/products/1144020c1"
    },
    "1151020c1": {
      "last_seen_at": "2026-07-21T04:30:54.237028+00:00",
      "name": "Principal matcha Kinrin \u00a53,000+ $18.47+ \u20ac 16 .18+ \u00a3 13 .74+ \u00a5124 .77+",
      "status": "IN_STOCK",
      "url": "https://www.marukyu-koyamaen.co.jp/english/shop/products/1151020c1"
    },
    "1152020c1": {
      "last_seen_at": "2026-07-21T04:30:54.237234+00:00",
      "name": "Urasenke Konnichian HOUNSAI Sosho Urasenke School Favored Matcha Shoun no Mukashi \u00a54,200+ $25.85+ \u20ac 22 .65+ \u00a3 19 .23+ \u00a5174 .68+",
      "status": "OUT_OF_STOCK",
      "url": "https://www.marukyu-koyamaen.co.jp/english/shop/products/1152020c1"
    },
    "1153020c1": {
      "last_seen_at": "2026-07-21T04:30:54.237674+00:00",
      "name": "Enshuryu Fudenan KOBORISOJITSU Iemoto Enshuryu School Favored Matcha Hatsu no Mori \u00a52,400+ $14.77+ \u20ac 12 .94+ \u00a3 10 .99+ \u00a599 .82+",
      "status": "OUT_OF_STOCK",
      "url": "https://www.marukyu-koyamaen.co.jp/english/shop/products/1153020c1"
    },
    "1154020c1": {
      "last_seen_at": "2026-07-21T04:30:54.237587+00:00",
      "name": "Yabunouchi Ennan SEISEISAI Iemoto Yabunouchi School Favored Matcha Ao no Mori \u00a52,400+ $14.77+ \u20ac 12 .94+ \u00a3 10 .99+ \u00a599 .82+",
      "status": "OUT_OF_STOCK",
      "url": "https://www.marukyu-koyamaen.co.jp/english/shop/products/1154020c1"
    },
    "1161020c1": {
      "last_seen_at": "2026-07-21T04:30:54.237320+00:00",
      "name": "Principal matcha Wako \u00a52,400+ $14.77+ \u20ac 12 .94+ \u00a3 10 .99+ \u00a599 .82+",
      "status": "OUT_OF_STOCK",
      "url": "https://www.marukyu-koyamaen.co.jp/english/shop/products/1161020c1"
    },
    "1171020c1": {
      "last_seen_at": "2026-07-21T04:30:54.236976+00:00",
      "name": "Principal matcha Yugen \u00a52,000+ $12.31+ \u20ac 10 .79+ \u00a3 9 .16+ \u00a583 .18+",
      "status": "IN_STOCK",
      "url": "https://www.marukyu-koyamaen.co.jp/english/shop/products/1171020c1"
    },
    "1172020c1": {
      "last_seen_at": "2026-07-21T04:30:54.237379+00:00",
      "name": "Urasenke Konnichian ZABOSAI Iemoto Urasenke School Favored Matcha Shoka no Mukashi \u00a54,200+ $25.85+ \u20ac 22 .65+ \u00a3 19 .23+ \u00a5174 .68+",
      "status": "OUT_OF_STOCK",
      "url": "https://www.marukyu-koyamaen.co.jp/english/shop/products/1172020c1"
    },
    "1174040c1": {
      "last_seen_at": "2026-07-21T04:30:54.237742+00:00",
      "name": "Shokokuji Temple Favored Shokokuji Temple Favored Matcha Mannen no Midori \u00a57,120 $43.83 \u20ac 38 .40 \u00a3 32 .60 \u00a5296 .12",
      "status": "OUT_OF_STOCK",
      "url": "https://www.marukyu-koyamaen.co.jp/english/shop/products/1174040c1"
    },
    "1181040c1": {
      "last_seen_at": "2026-07-21T04:30:54.237045+00:00",
      "name": "Principal matcha Chigi no Shiro \u00a52,920+ $17.97+ \u20ac 15 .75+ \u00a3 13 .37+ \u00a5121 .44+",
      "status": "IN_STOCK",
      "url": "https://www.marukyu-koyamaen.co.jp/english/shop/products/1181040c1"
    },
    "1182020c1": {
      "last_seen_at": "2026-07-21T04:30:54.237398+00:00",
      "name": "Urasenke Konnichian ZABOSAI Iemoto Urasenke School Favored Matcha Seijo no Shiro \u00a52,400+ $14.77+ \u20ac 12 .94+ \u00a3 10 .99+ \u00a599 .82+",
      "status": "OUT_OF_STOCK",
      "url": "https://www.marukyu-koyamaen.co.jp/english/shop/products/1182020c1"
    },
    "1183040c1": {
      "last_seen_at": "2026-07-21T04:30:54.237759+00:00",
      "name": "Sohenryu Fushinan YUYUSAI Iemoto Sohenryu School Favored Matcha Kokonoe no Mukashi \u00a57,120+ $43.83+ \u20ac 38 .40+ \u00a3 32 .60+ \u00a5296 .12+",
      "status": "OUT_OF_STOCK",
      "url": "https://www.marukyu-koyamaen.co.jp/english/shop/products/1183040c1"
    },
    "1184040c1": {
      "last_seen_at": "2026-07-21T04:30:54.237774+00:00",
      "name": "Shokokuji Temple Favored Shokokuji Temple Favored Matcha Joko \u00a54,520 $27.82 \u20ac 24 .37 \u00a3 20 .70 \u00a5187 .99",
      "status": "OUT_OF_STOCK",
      "url": "https://www.marukyu-koyamaen.co.jp/english/shop/products/1184040c1"
    },
    "1186000cc": {
      "last_seen_at": "2026-07-21T04:30:54.237106+00:00",
      "name": "Sweetened Matcha Sweetened Matcha \u2013 Excellent \u00a51,200+ $7.39+ \u20ac 6 .47+ \u00a3 5 .49+ \u00a549 .91+",
      "status": "IN_STOCK",
      "url": "https://www.marukyu-koyamaen.co.jp/english/shop/products/1186000cc"
    },
    "1191040c1": {
      "last_seen_at": "2026-07-21T04:30:54.237064+00:00",
      "name": "Principal matcha Isuzu \u00a52,520+ $15.51+ \u20ac 13 .59+ \u00a3 11 .54+ \u00a5104 .81+",
      "status": "IN_STOCK",
      "url": "https://www.marukyu-koyamaen.co.jp/english/shop/products/1191040c1"
    },
    "1192020c1": {
      "last_seen_at": "2026-07-21T04:30:54.237493+00:00",
      "name": "Omotesenke Fushin'an JIMYOSAI Sosho Omotesenke School Favored Matcha Myofu no Mukashi \u00a54,700+ $28.93+ \u20ac 25 .35+ \u00a3 21 .52+ \u00a5195 .47+",
      "status": "OUT_OF_STOCK",
      "url": "https://www.marukyu-koyamaen.co.jp/english/shop/products/1192020c1"
    },
    "11a1040c1": {
      "last_seen_at": "2026-07-21T04:30:54.237087+00:00",
      "name": "Principal matcha Aoarashi \u00a52,120+ $13.05+ \u20ac 11 .43+ \u00a3 9 .71+ \u00a588 .17+",
      "status": "IN_STOCK",
      "url": "https://www.marukyu-koyamaen.co.jp/english/shop/products/11a1040c1"
    },
    "11a2020c1": {
      "last_seen_at": "2026-07-21T04:30:54.237511+00:00",
      "name": "Omotesenke Fushin'an JIMYOSAI Sosho Omotesenke School Favored Matcha Saiun \u00a53,700+ $22.78+ \u20ac 19 .95+ \u00a3 16 .94+ \u00a5153 .88+",
      "status": "OUT_OF_STOCK",
      "url": "https://www.marukyu-koyamaen.co.jp/english/shop/products/11a2020c1"
    },
    "11a4040c1": {
      "last_seen_at": "2026-07-21T04:30:54.237789+00:00",
      "name": "Daitokuji Temple Favored Daitokuji Temple Favored Matcha Itteikisui \u00a55,720 $35.21 \u20ac 30 .85 \u00a3 26 .19 \u00a5237 .89",
      "status": "OUT_OF_STOCK",
      "url": "https://www.marukyu-koyamaen.co.jp/english/shop/products/11a4040c1"
    },
    "11a5020c1": {
      "last_seen_at": "2026-06-26T01:55:54.405704+00:00",
      "name": "Limited Edition Teas Shin Matcha Hatsu Kaori $18.55+",
      "status": "OUT_OF_STOCK",
      "url": "https://www.marukyu-koyamaen.co.jp/english/shop/products/11a5020c1"
    },
    "11b1100c1": {
      "last_seen_at": "2026-07-21T04:30:54.236899+00:00",
      "name": "Matcha for Cooking Wakatake \u00a53,340+ $20.56+ \u20ac 18 .01+ \u00a3 15 .29+ \u00a5138 .91+",
      "status": "IN_STOCK",
      "url": "https://www.marukyu-koyamaen.co.jp/english/shop/products/11b1100c1"
    },
    "11b2040c1": {
      "last_seen_at": "2026-07-21T04:30:54.237567+00:00",
      "name": "Omotesenke Fushin'an JIMYOSAI Sosho Omotesenke School Favored Matcha Sanyu no Shiro \u00a54,520 $27.82 \u20ac 24 .37 \u00a3 20 .70 \u00a5187 .99",
      "status": "OUT_OF_STOCK",
      "url": "https://www.marukyu-koyamaen.co.jp/english/shop/products/11b2040c1"
    },
    "11b5040c1": {
      "last_seen_at": "2026-07-21T04:30:54.237285+00:00",
      "name": "Limited Edition Teas Gabaron Matcha \u00a53,920 $24.13 \u20ac 21 .14 \u00a3 17 .95 \u00a5163 .03",
      "status": "OUT_OF_STOCK",
      "url": "https://www.marukyu-koyamaen.co.jp/english/shop/products/11b5040c1"
    },
    "11c2020c1": {
      "last_seen_at": "2026-07-21T04:30:54.237529+00:00",
      "name": "Omotesenke Fushin'an JIMYOSAI Sosho Omotesenke School Favored Matcha Kissho \u00a52,000+ $12.31+ \u20ac 10 .79+ \u00a3 9 .16+ \u00a583 .18+",
      "status": "OUT_OF_STOCK",
      "url": "https://www.marukyu-koyamaen.co.jp/english/shop/products/11c2020c1"
    },
    "11c3020c1": {
      "last_seen_at": "2026-07-21T04:30:54.237691+00:00",
      "name": "Sohenryu Fushinan YUYUSAI Iemoto Sohenryu School Favored Matcha Miya no Shiro \u00a53,000+ $18.47+ \u20ac 16 .18+ \u00a3 13 .74+ \u00a5124 .77+",
      "status": "OUT_OF_STOCK",
      "url": "https://www.marukyu-koyamaen.co.jp/english/shop/products/11c3020c1"
    },
    "1262040c1": {
      "last_seen_at": "2026-07-21T04:30:54.237303+00:00",
      "name": "Matcha for Cooking Cooking Matcha (in a sifter can) \u2013 Excellent \u00a51,720 $10.59 \u20ac 9 .28 \u00a3 7 .88 \u00a571 .53",
      "status": "OUT_OF_STOCK",
      "url": "https://www.marukyu-koyamaen.co.jp/english/shop/products/1262040c1"
    },
    "1c55000cc": {
      "last_seen_at": "2026-07-21T04:30:54.237126+00:00",
      "name": "Sweetened Matcha Sweetened Matcha \u2013 Designed For Milk \u00a51,200+ $7.39+ \u20ac 6 .47+ \u00a3 5 .49+ \u00a549 .91+",
      "status": "IN_STOCK",
      "url": "https://www.marukyu-koyamaen.co.jp/english/shop/products/1c55000cc"
    },
    "1d23040c1": {
      "last_seen_at": "2026-07-21T04:30:54.237822+00:00",
      "name": "Sohenryu Fushinan YUYUSAI Iemoto Sohenryu School Favored Matcha Tomo no Shiro \u00a53,720+ $22.90+ \u20ac 20 .06+ \u00a3 17 .03+ \u00a5154 .71+",
      "status": "OUT_OF_STOCK",
      "url": "https://www.marukyu-koyamaen.co.jp/english/shop/products/1d23040c1"
    },
    "1d9d000cc": {
      "last_seen_at": "2026-07-21T04:30:54.237214+00:00",
      "name": "Sweetened Matcha Matcha Soda \u00a51,250+ $7.69+ \u20ac 6 .74+ \u00a3 5 .72+ \u00a551 .99+",
      "status": "IN_STOCK",
      "url": "https://www.marukyu-koyamaen.co.jp/english/shop/products/1d9d000cc"
    },
    "1dbd020c1": {
      "last_seen_at": "2026-07-21T04:30:54.237180+00:00",
      "name": "Limited Edition Teas Matcha for cold water Suzukumo \u00a52,900+ $17.85+ \u20ac 15 .64+ \u00a3 13 .28+ \u00a5120 .61+",
      "status": "IN_STOCK",
      "url": "https://www.marukyu-koyamaen.co.jp/english/shop/products/1dbd020c1"
    },
    "1dcd020c1": {
      "last_seen_at": "2026-07-21T04:30:54.237805+00:00",
      "name": "Limited Edition Teas Matcha for cold water Awaraku \u00a52,100+ $12.93+ \u20ac 11 .32+ \u00a3 9 .62+ \u00a587 .34+",
      "status": "OUT_OF_STOCK",
      "url": "https://www.marukyu-koyamaen.co.jp/english/shop/products/1dcd020c1"
    },
    "1f52020c1": {
      "last_seen_at": "2026-07-21T04:30:54.237340+00:00",
      "name": "Yabunouchi Ennan INYUSAI Iemoto Yabunouchi School Iemoto Favored Matcha Hekiun no Mukashi \u00a53,700+ $22.78+ \u20ac 19 .95+ \u00a3 16 .94+ \u00a5153 .88+",
      "status": "OUT_OF_STOCK",
      "url": "https://www.marukyu-koyamaen.co.jp/english/shop/products/1f52020c1"
    },
    "1f62020c1": {
      "last_seen_at": "2026-07-21T04:30:54.237360+00:00",
      "name": "Yabunouchi Ennan INYUSAI Iemoto Yabunouchi School Iemoto Favored Matcha Yoyo no Shiro \u00a52,400+ $14.77+ \u20ac 12 .94+ \u00a3 10 .99+ \u00a599 .82+",
      "status": "OUT_OF_STOCK",
      "url": "https://www.marukyu-koyamaen.co.jp/english/shop/products/1f62020c1"
    },
    "1f68020c1": {
      "last_seen_at": "2026-07-21T04:30:54.237607+00:00",
      "name": "Omotesenke Fushin'an YUYUSAI Iemoto Omotesenke School Yuyusai Iemoto Favored Matcha Saiho no Mukashi \u00a54,200+ $25.85+ \u20ac 22 .65+ \u00a3 19 .23+ \u00a5174 .68+",
      "status": "OUT_OF_STOCK",
      "url": "https://www.marukyu-koyamaen.co.jp/english/shop/products/1f68020c1"
    },
    "1f78020c1": {
      "last_seen_at": "2026-07-21T04:30:54.237549+00:00",
      "name": "Omotesenke Fushin'an YUYUSAI Iemoto Omotesenke School Yuyusai Iemoto Favored Matcha Yukyu no Shiro \u00a52,400+ $14.77+ \u20ac 12 .94+ \u00a3 10 .99+ \u00a599 .82+",
      "status": "OUT_OF_STOCK",
      "url": "https://www.marukyu-koyamaen.co.jp/english/shop/products/1f78020c1"
    },
    "1f94020c1": {
      "last_seen_at": "2026-07-21T04:30:54.237161+00:00",
      "name": "Limited Edition Teas Low Caffeine Matcha \u00a52,200+ $13.54+ \u20ac 11 .86+ \u00a3 10 .07+ \u00a591 .50+",
      "status": "IN_STOCK",
      "url": "https://www.marukyu-koyamaen.co.jp/english/shop/products/1f94020c1"
    },
    "1g28200c6": {
      "last_seen_at": "2026-07-21T04:30:54.237143+00:00",
      "name": "Sweetened Matcha Hojicha Mix \u00a5800 $4.92 \u20ac 4 .31 \u00a3 3 .66 \u00a533 .27",
      "status": "IN_STOCK",
      "url": "https://www.marukyu-koyamaen.co.jp/english/shop/products/1g28200c6"
    },
    "1g36020c1": {
      "last_seen_at": "2026-07-21T04:30:54.237251+00:00",
      "name": "Principal matcha Kiwami Choan \u00a512,600+ $77.56+ \u20ac 67 .95+ \u00a3 57 .70+ \u00a5524 .03+",
      "status": "OUT_OF_STOCK",
      "url": "https://www.marukyu-koyamaen.co.jp/english/shop/products/1g36020c1"
    },
    "1g9d000cc": {
      "last_seen_at": "2026-07-21T04:30:54.237197+00:00",
      "name": "Sweetened Matcha Matcha Mix \u00a51,300+ $8.00+ \u20ac 7 .01+ \u00a3 5 .95+ \u00a554 .07+",
      "status": "IN_STOCK",
      "url": "https://www.marukyu-koyamaen.co.jp/english/shop/products/1g9d000cc"
    }
  },
  "telegram": {
    "last_update_id": 534314920,
    "subscribers": {
      "383420669": {
        "first_name": "Sevara",
        "subscribed_at": "2026-06-03T22:23:58.432307+00:00",
        "username": "sevbad"
      },
      "787099075": {
        "first_name": "Dana",
        "subscribed_at": "2026-06-03T22:23:58.011388+00:00",
        "username": "danaa_1610"
      },
      "8623708194": {
        "first_name": "Brenda",
        "subscribed_at": "2026-07-17T10:22:31.516833+00:00",
        "username": null
      }
    }
  }
}
